netlsd
