Metadata-Version: 1.1
Name: NetLSD
Version: 1.0.2
Summary: NetLSD descriptors for graphs. Compare and analyze graph structure on multiple levels!
Home-page: http://github.com/xgfs/netlsd
Author: Anton Tsitsulin
Author-email: anton.tsitsulin@hpi.de
License: MIT
Download-URL: https://github.com/xgfs/netlsd/archive/0.1.tar.gz
Platform: UNKNOWN
Classifier: Development Status :: 3 - Alpha
Classifier: License :: OSI Approved :: MIT License
Classifier: Programming Language :: Python :: 2.7
Classifier: Programming Language :: Python :: 3.5
Classifier: Topic :: Scientific/Engineering :: Mathematics
Classifier: Topic :: Scientific/Engineering :: Artificial Intelligence
